<?xml version="1.0" encoding="UTF-8"?>
<objects serializationModel="Studio.02.02.00">
	<object class="AudioFile" id="{ab18d3db-e66c-44cc-b077-cce5fae5c22d}">
		<property name="assetPath">
			<value>Espawn04 [2022-10-02 203533].wav</value>
		</property>
		<property name="frequencyInKHz">
			<value>44.0999985</value>
		</property>
		<property name="channelCount">
			<value>2</value>
		</property>
		<property name="length">
			<value>1</value>
		</property>
		<relationship name="masterAssetFolder">
			<destination>{43badae5-e16c-47df-9693-00c5a3633ebe}</destination>
		</relationship>
	</object>
</objects>
